pmfp/__init__.py
pmfp/__main__.py
pmfp/const.py
pmfp/protocol.py
pmfp/entrypoint/__init__.py
pmfp/entrypoint/core.py
pmfp/entrypoint/info.py
pmfp/entrypoint/run.py
pmfp/entrypoint/version.py
pmfp/entrypoint/build_/__init__.py
pmfp/entrypoint/build_/build_go.py
pmfp/entrypoint/build_/build_py.py
pmfp/entrypoint/build_/core.py
pmfp/entrypoint/build_/utils.py
pmfp/entrypoint/cache/__init__.py
pmfp/entrypoint/cache/core.py
pmfp/entrypoint/cache/info.py
pmfp/entrypoint/cache/list.py
pmfp/entrypoint/cache/clean/__init__.py
pmfp/entrypoint/cache/clean/core.py
pmfp/entrypoint/cache/get/__init__.py
pmfp/entrypoint/cache/get/core.py
pmfp/entrypoint/doc_/__init__.py
pmfp/entrypoint/doc_/core.py
pmfp/entrypoint/doc_/utils.py
pmfp/entrypoint/doc_/build_/__init__.py
pmfp/entrypoint/doc_/build_/build_go.py
pmfp/entrypoint/doc_/build_/build_py.py
pmfp/entrypoint/doc_/build_/core.py
pmfp/entrypoint/doc_/new/__init__.py
pmfp/entrypoint/doc_/new/core.py
pmfp/entrypoint/doc_/new/new_go.py
pmfp/entrypoint/doc_/new/new_py.py
pmfp/entrypoint/doc_/new/source_temp/__init__.py
pmfp/entrypoint/doc_/new/source_temp/cppappend_config.py.jinja
pmfp/entrypoint/doc_/new/source_temp/pyappend_config.py.jinja
pmfp/entrypoint/doc_/new/source_temp/pyindex.md.jinja
pmfp/entrypoint/docker_/__init__.py
pmfp/entrypoint/docker_/core.py
pmfp/entrypoint/docker_/compose/__init__.py
pmfp/entrypoint/docker_/compose/core.py
pmfp/entrypoint/docker_/compose/deploy/__init__.py
pmfp/entrypoint/docker_/compose/deploy/core.py
pmfp/entrypoint/docker_/compose/deploy/deploy_local.py
pmfp/entrypoint/docker_/compose/deploy/deploy_portainer.py
pmfp/entrypoint/docker_/compose/new/__init__.py
pmfp/entrypoint/docker_/compose/new/core.py
pmfp/entrypoint/docker_/compose/new/merge_compose_dict.py
pmfp/entrypoint/docker_/compose/new/new_compose_dict.py
pmfp/entrypoint/docker_/compose/new/save_compose.py
pmfp/entrypoint/docker_/compose/new/typedef.py
pmfp/entrypoint/docker_/image/__init__.py
pmfp/entrypoint/docker_/image/core.py
pmfp-4.1.11.dist-info/LICENSE
pmfp-4.1.11.dist-info/METADATA
pmfp-4.1.11.dist-info/WHEEL
pmfp-4.1.11.dist-info/entry_points.txt
pmfp-4.1.11.dist-info/top_level.txt
pmfp-4.1.11.dist-info/RECORD
