Metadata-Version: 2.1
Name: pmfp
Version: 4.1.11
Summary: A simple package manager and scaffold for python & some other languages.
Home-page: https://github.com/Python-Tools/pmfp
Author: hsz
Author-email: hsz1273327@gmail.com
License: MIT License
Keywords: config,environment variable,command line arguments,config file
Classifier: License :: OSI Approved :: MIT License
Classifier: Programming Language :: Python :: 3.6
Classifier: Programming Language :: Python :: 3.7
Classifier: Programming Language :: Python :: 3.8
Classifier: Programming Language :: Python :: 3.9
Classifier: Programming Language :: Python :: 3.10
Classifier: Topic :: Documentation :: Sphinx
License-File: LICENSE
Requires-Dist: wheel (>=0.36.2)
Requires-Dist: Pygments (>=2.9.0)
Requires-Dist: Babel (>=2.9.1)
Requires-Dist: mypy (>=0.800)
Requires-Dist: schema-entry (>=0.1.5)
Requires-Dist: colorama (>=0.4.0)
Requires-Dist: termcolor (>=1.0.0)
Requires-Dist: jsonschema (>=3.2.0)
Requires-Dist: requests (>=2.24.0)
Requires-Dist: requests-oauthlib (>=1.3.0)
Requires-Dist: GitPython (>=3.1.5)
Requires-Dist: pyaml (>=20.4.0)
Requires-Dist: toml (>=0.10.1)
Requires-Dist: jinja2 (>=2.11)
Requires-Dist: sphinx (>=3.5)
Requires-Dist: coverage (>=5.5)
Requires-Dist: recommonmark (>=0.7.1)
Requires-Dist: sphinxcontrib-napoleon (>=0.7)
Requires-Dist: sphinx-intl (>=2.0.1)
Requires-Dist: sphinx-autoapi (>=1.8.1)
Requires-Dist: sphinx-rtd-theme (>=0.5.2)
Requires-Dist: astroid (>=2.7)
